nitrogfx/__init__.py
nitrogfx/convert.py
nitrogfx/nanr.py
nitrogfx/ncer.py
nitrogfx/ncgr.py
nitrogfx/nclr.py
nitrogfx/nscr.py
nitrogfx/util.py
nitrogfx_py-0.2.0.dist-info/LICENSE.txt
nitrogfx_py-0.2.0.dist-info/METADATA
nitrogfx_py-0.2.0.dist-info/WHEEL
nitrogfx_py-0.2.0.dist-info/top_level.txt
nitrogfx_py-0.2.0.dist-info/RECORD
