Metadata-Version: 2.1
Name: nitrogfx-py
Version: 0.2.0
Summary: Nintendo DS Graphic format library
Author-email: Fexean <3699814-Fexean@users.noreply.gitlab.com>
License: GNU GENERAL PUBLIC LICENSE
Project-URL: Homepage, https://gitlab.com/Fexean/ntrgfx-py
Keywords: NDS,Nintendo DS,NCGR,NCLR,NSCR,NCER,NANR
Classifier: Programming Language :: Python :: 3
Classifier: License :: OSI Approved :: GNU General Public License v3 or later (GPLv3+)
Classifier: Operating System :: OS Independent
Requires-Python: >=3.7
License-File: LICENSE.txt
Requires-Dist: Pillow (==7.0.0)
